pytmx/__init__.py
pytmx/pytmx.py
pytmx/util_pygame.py
pytmx/util_pygame_sdl2.py
pytmx/util_pyglet.py
pytmx/util_pysdl2.py
PyTMX-3.32.dist-info/LICENSE
PyTMX-3.32.dist-info/METADATA
PyTMX-3.32.dist-info/WHEEL
PyTMX-3.32.dist-info/top_level.txt
PyTMX-3.32.dist-info/RECORD
