Metadata-Version: 2.1
Name: PyTMX
Version: 3.32
Summary: Loads tiled tmx maps
Home-page: UNKNOWN
Author: bitcraft
Author-email: leif.theden@gmail.com
License: LGPLv3
Platform: UNKNOWN
Classifier: Intended Audience :: Developers
Classifier: Development Status :: 5 - Production/Stable
Classifier: License :: OSI Approved :: GNU Lesser General Public License v3 (LGPLv3)
Classifier: Programming Language :: Python :: 3.7
Classifier: Programming Language :: Python :: 3.8
Classifier: Programming Language :: Python :: 3.9
Classifier: Programming Language :: Python :: 3.10
Classifier: Programming Language :: Python :: 3.11
Classifier: Topic :: Games/Entertainment
Classifier: Topic :: Multimedia :: Graphics
Classifier: Topic :: Software Development :: Libraries :: pygame
Requires-Python: >=3.7
Provides-Extra: pygame
Provides-Extra: pygame-ce
License-File: LICENSE
